{
    "WFWorkflowMinimumClientVersionString": "900",
    "WFWorkflowMinimumClientVersion": 900,
    "WFWorkflowIcon": {
        "WFWorkflowIconStartColor": 2846468607,
        "WFWorkflowIconGlyphNumber": 61440
    },
    "WFWorkflowClientVersion": "4046.0.2.2",
    "WFWorkflowOutputContentItemClasses": [],
    "WFWorkflowHasOutputFallback": false,
    "WFWorkflowActions": [
        {
            "WFWorkflowActionIdentifier": "is.workflow.actions.comment",
            "WFWorkflowActionParameters": {
                "WFCommentActionText": "👇 Read on website\n──────────────\nhttps://huami.ng/dear-today-me"
            }
        },
        {
            "WFWorkflowActionIdentifier": "is.workflow.actions.lockscreen",
            "WFWorkflowActionParameters": {}
        },
        {
            "WFWorkflowActionIdentifier": "is.workflow.actions.setvolume",
            "WFWorkflowActionParameters": {
                "WFVolume": 0.8474746942520142,
                "WFVolumeSetting": "Media"
            }
        },
        {
            "WFWorkflowActionIdentifier": "is.workflow.actions.downloadurl",
            "WFWorkflowActionParameters": {
                "WFURL": "https://raw.githubusercontent.com/huaminghuangtw/Dear-Today-Me/main/Dear-Today-Me.md",
                "UUID": "13105FF1-E401-4904-80A4-E3B856C0F227"
            }
        },
        {
            "WFWorkflowActionIdentifier": "is.workflow.actions.gettext",
            "WFWorkflowActionParameters": {
                "WFTextActionText": "\n\n",
                "CustomOutputName": "\\n\\n",
                "UUID": "C2288ED8-2534-49D8-82E4-C8FA7F6E60C6"
            }
        },
        {
            "WFWorkflowActionIdentifier": "is.workflow.actions.text.split",
            "WFWorkflowActionParameters": {
                "WFTextCustomSeparator": {
                    "Value": {
                        "string": "￼",
                        "attachmentsByRange": {
                            "{0, 1}": {
                                "OutputUUID": "C2288ED8-2534-49D8-82E4-C8FA7F6E60C6",
                                "Type": "ActionOutput",
                                "OutputName": "\\n\\n"
                            }
                        }
                    },
                    "WFSerializationType": "WFTextTokenString"
                },
                "UUID": "0CE45B4F-5E5A-40B8-AFC9-014E560AF608",
                "WFTextSeparator": "Custom",
                "text": {
                    "Value": {
                        "OutputUUID": "13105FF1-E401-4904-80A4-E3B856C0F227",
                        "Type": "ActionOutput",
                        "OutputName": "Contents of URL"
                    },
                    "WFSerializationType": "WFTextTokenAttachment"
                }
            }
        },
        {
            "WFWorkflowActionIdentifier": "is.workflow.actions.count",
            "WFWorkflowActionParameters": {
                "Input": {
                    "Value": {
                        "OutputUUID": "0CE45B4F-5E5A-40B8-AFC9-014E560AF608",
                        "Type": "ActionOutput",
                        "OutputName": "Split Text"
                    },
                    "WFSerializationType": "WFTextTokenAttachment"
                },
                "UUID": "2448E32D-0E0F-4586-817C-3F05EB8FE9F8"
            }
        },
        {
            "WFWorkflowActionIdentifier": "is.workflow.actions.math",
            "WFWorkflowActionParameters": {
                "WFInput": {
                    "Value": {
                        "OutputUUID": "2448E32D-0E0F-4586-817C-3F05EB8FE9F8",
                        "Type": "ActionOutput",
                        "OutputName": "Count"
                    },
                    "WFSerializationType": "WFTextTokenAttachment"
                },
                "WFMathOperand": "2",
                "UUID": "2028F74B-F751-470A-8FBF-8FA05AAFFCBB",
                "WFMathOperation": "-"
            }
        },
        {
            "WFWorkflowActionIdentifier": "is.workflow.actions.comment",
            "WFWorkflowActionParameters": {
                "WFCommentActionText": "Skip salutation and closing lines"
            }
        },
        {
            "WFWorkflowActionIdentifier": "is.workflow.actions.getitemfromlist",
            "WFWorkflowActionParameters": {
                "WFInput": {
                    "Value": {
                        "OutputUUID": "0CE45B4F-5E5A-40B8-AFC9-014E560AF608",
                        "Type": "ActionOutput",
                        "OutputName": "Split Text"
                    },
                    "WFSerializationType": "WFTextTokenAttachment"
                },
                "WFItemSpecifier": "Items in Range",
                "WFItemRangeEnd": {
                    "Value": {
                        "OutputUUID": "2028F74B-F751-470A-8FBF-8FA05AAFFCBB",
                        "Type": "ActionOutput",
                        "OutputName": "Calculation Result"
                    },
                    "WFSerializationType": "WFTextTokenAttachment"
                },
                "UUID": "0307C3C5-00C2-43E4-988C-994723B60A53",
                "WFItemRangeStart": "2"
            }
        },
        {
            "WFWorkflowActionIdentifier": "is.workflow.actions.getitemfromlist",
            "WFWorkflowActionParameters": {
                "WFInput": {
                    "Value": {
                        "OutputUUID": "0307C3C5-00C2-43E4-988C-994723B60A53",
                        "Type": "ActionOutput",
                        "OutputName": "Item from List"
                    },
                    "WFSerializationType": "WFTextTokenAttachment"
                },
                "WFItemSpecifier": "Random Item",
                "UUID": "3B7F90E4-F87A-4649-A31B-11070544974A"
            }
        },
        {
            "WFWorkflowActionIdentifier": "is.workflow.actions.getrichtextfrommarkdown",
            "WFWorkflowActionParameters": {
                "WFInput": {
                    "Value": {
                        "OutputUUID": "3B7F90E4-F87A-4649-A31B-11070544974A",
                        "Type": "ActionOutput",
                        "OutputName": "Item from List"
                    },
                    "WFSerializationType": "WFTextTokenAttachment"
                },
                "UUID": "2D56ACA9-CA72-46FF-8D4C-B183A9F12573"
            }
        },
        {
            "WFWorkflowActionIdentifier": "is.workflow.actions.makespokenaudiofromtext",
            "WFWorkflowActionParameters": {
                "WFInput": {
                    "Value": {
                        "string": "￼",
                        "attachmentsByRange": {
                            "{0, 1}": {
                                "OutputUUID": "2D56ACA9-CA72-46FF-8D4C-B183A9F12573",
                                "Type": "ActionOutput",
                                "OutputName": "Rich Text from Markdown"
                            }
                        }
                    },
                    "WFSerializationType": "WFTextTokenString"
                },
                "WFSpeakTextPitch": 0.9002242088317871,
                "UUID": "CDBB57E5-D1C6-4793-9358-86A0A8C27ED1",
                "WFSpeakTextLanguage": "en-US",
                "WFSpeakTextRate": 0.40433478355407715,
                "WFSpeakTextVoice": "com.apple.ttsbundle.siri_Aaron_en-US_compact"
            }
        },
        {
            "WFWorkflowActionIdentifier": "is.workflow.actions.playsound",
            "WFWorkflowActionParameters": {
                "WFInput": {
                    "Value": {
                        "OutputUUID": "CDBB57E5-D1C6-4793-9358-86A0A8C27ED1",
                        "Type": "ActionOutput",
                        "OutputName": "Spoken Audio"
                    },
                    "WFSerializationType": "WFTextTokenAttachment"
                }
            }
        },
        {
            "WFWorkflowActionIdentifier": "is.workflow.actions.runworkflow",
            "WFWorkflowActionParameters": {
                "WFWorkflowName": "Your Pocket Life Coach",
                "WFWorkflow": {
                    "workflowIdentifier": "E3B707EA-3BC9-4F07-BEE4-839DE82F64F4",
                    "workflowName": "Your Pocket Life Coach",
                    "isSelf": true
                }
            }
        },
        {
            "WFWorkflowActionIdentifier": "is.workflow.actions.exit",
            "WFWorkflowActionParameters": {}
        }
    ],
    "WFWorkflowInputContentItemClasses": [
        "WFAppContentItem",
        "WFAppStoreAppContentItem",
        "WFArticleContentItem",
        "WFContactContentItem",
        "WFDateContentItem",
        "WFEmailAddressContentItem",
        "WFFolderContentItem",
        "WFGenericFileContentItem",
        "WFImageContentItem",
        "WFiTunesProductContentItem",
        "WFLocationContentItem",
        "WFDCMapsLinkContentItem",
        "WFAVAssetContentItem",
        "WFPDFContentItem",
        "WFPhoneNumberContentItem",
        "WFRichTextContentItem",
        "WFSafariWebPageContentItem",
        "WFStringContentItem",
        "WFURLContentItem"
    ],
    "WFWorkflowImportQuestions": [],
    "WFWorkflowTypes": [
        "Watch"
    ],
    "WFQuickActionSurfaces": [],
    "WFWorkflowHasShortcutInputVariables": false
}