{
    "WFWorkflowMinimumClientVersionString": "900",
    "WFWorkflowMinimumClientVersion": 900,
    "WFWorkflowIcon": {
        "WFWorkflowIconStartColor": 2846468607,
        "WFWorkflowIconGlyphNumber": 61440
    },
    "WFWorkflowClientVersion": "4046.0.2.2",
    "WFWorkflowOutputContentItemClasses": [],
    "WFWorkflowHasOutputFallback": false,
    "WFWorkflowActions": [
        {
            "WFWorkflowActionIdentifier": "is.workflow.actions.conditional",
            "WFWorkflowActionParameters": {
                "WFInput": {
                    "Type": "Variable",
                    "Variable": {
                        "Value": {
                            "Type": "ExtensionInput"
                        },
                        "WFSerializationType": "WFTextTokenAttachment"
                    }
                },
                "WFControlFlowMode": 0,
                "GroupingIdentifier": "42A5302A-FE67-4F6F-9D08-BD79806287A6",
                "WFCondition": 100
            }
        },
        {
            "WFWorkflowActionIdentifier": "is.workflow.actions.repeat.each",
            "WFWorkflowActionParameters": {
                "WFInput": {
                    "Value": {
                        "Type": "ExtensionInput"
                    },
                    "WFSerializationType": "WFTextTokenAttachment"
                },
                "GroupingIdentifier": "69CA1114-0496-4FFD-8765-C840B4843648",
                "WFControlFlowMode": 0
            }
        },
        {
            "WFWorkflowActionIdentifier": "is.workflow.actions.detect.date",
            "WFWorkflowActionParameters": {
                "WFInput": {
                    "Value": {
                        "VariableName": "Repeat Item",
                        "Type": "Variable"
                    },
                    "WFSerializationType": "WFTextTokenAttachment"
                },
                "UUID": "7BBE80FB-DFB8-491E-9ED6-5AB61199C5C4"
            }
        },
        {
            "WFWorkflowActionIdentifier": "is.workflow.actions.repeat.each",
            "WFWorkflowActionParameters": {
                "WFControlFlowMode": 2,
                "GroupingIdentifier": "69CA1114-0496-4FFD-8765-C840B4843648",
                "UUID": "04B4A955-708A-4EBC-B552-6F09C380E3F5"
            }
        },
        {
            "WFWorkflowActionIdentifier": "is.workflow.actions.conditional",
            "WFWorkflowActionParameters": {
                "GroupingIdentifier": "42A5302A-FE67-4F6F-9D08-BD79806287A6",
                "WFControlFlowMode": 1
            }
        },
        {
            "WFWorkflowActionIdentifier": "is.workflow.actions.runworkflow",
            "WFWorkflowActionParameters": {
                "WFWorkflow": {
                    "workflowIdentifier": "BFA3F439-0E32-41A3-AF85-B6A51E0094F2",
                    "workflowName": "Select Date",
                    "isSelf": false
                },
                "CustomOutputName": "date",
                "UUID": "0B2779AA-D64E-4BEF-B61E-CC854722C70E",
                "WFWorkflowName": "Select Date"
            }
        },
        {
            "WFWorkflowActionIdentifier": "is.workflow.actions.conditional",
            "WFWorkflowActionParameters": {
                "WFControlFlowMode": 2,
                "GroupingIdentifier": "42A5302A-FE67-4F6F-9D08-BD79806287A6",
                "UUID": "92346EEA-B728-4256-ACBC-2500622E49DE"
            }
        },
        {
            "WFWorkflowActionIdentifier": "is.workflow.actions.repeat.each",
            "WFWorkflowActionParameters": {
                "WFInput": {
                    "Value": {
                        "OutputUUID": "92346EEA-B728-4256-ACBC-2500622E49DE",
                        "Type": "ActionOutput",
                        "OutputName": "If Result"
                    },
                    "WFSerializationType": "WFTextTokenAttachment"
                },
                "GroupingIdentifier": "B7D2A558-BE69-4152-A300-AC763CF37D31",
                "WFControlFlowMode": 0
            }
        },
        {
            "WFWorkflowActionIdentifier": "is.workflow.actions.conditional",
            "WFWorkflowActionParameters": {
                "GroupingIdentifier": "6402CF4A-B049-4768-A6DD-EEE9D2A8F831",
                "WFInput": {
                    "Type": "Variable",
                    "Variable": {
                        "Value": {
                            "Type": "DeviceDetails",
                            "Aggrandizements": [
                                {
                                    "Type": "WFPropertyVariableAggrandizement",
                                    "PropertyName": "OS"
                                }
                            ]
                        },
                        "WFSerializationType": "WFTextTokenAttachment"
                    }
                },
                "WFControlFlowMode": 0,
                "WFEnumeration": "macOS",
                "WFCondition": 4
            }
        },
        {
            "WFWorkflowActionIdentifier": "is.workflow.actions.runworkflow",
            "WFWorkflowActionParameters": {
                "WFInput": {
                    "Value": {
                        "VariableName": "Repeat Item",
                        "Type": "Variable"
                    },
                    "WFSerializationType": "WFTextTokenAttachment"
                },
                "WFWorkflow": {
                    "workflowIdentifier": "B2F430B0-7EC1-401A-89B0-B31F95B9C0D5",
                    "workflowName": "✏️ Create New Journal",
                    "isSelf": false
                },
                "UUID": "7F58803D-4115-4312-A34B-3F734A4C3372",
                "WFWorkflowName": "✏️ Create New Journal"
            }
        },
        {
            "WFWorkflowActionIdentifier": "is.workflow.actions.conditional",
            "WFWorkflowActionParameters": {
                "WFControlFlowMode": 2,
                "GroupingIdentifier": "6402CF4A-B049-4768-A6DD-EEE9D2A8F831",
                "UUID": "D7A7A4C5-401B-4CFE-A4FB-89657A56480B"
            }
        },
        {
            "WFWorkflowActionIdentifier": "is.workflow.actions.runworkflow",
            "WFWorkflowActionParameters": {
                "WFInput": {
                    "Value": {
                        "VariableName": "Repeat Item",
                        "Type": "Variable"
                    },
                    "WFSerializationType": "WFTextTokenAttachment"
                },
                "CustomOutputName": "filepath",
                "UUID": "8072BE04-FF3C-4C42-B193-630B85655D7E",
                "WFWorkflow": {
                    "workflowIdentifier": "C69C14F5-C839-4081-BFBB-85636C0A708B",
                    "workflowName": "Query Journals on Date",
                    "isSelf": false
                },
                "WFWorkflowName": "Query Journals on Date"
            }
        },
        {
            "WFWorkflowActionIdentifier": "is.workflow.actions.dictionary",
            "WFWorkflowActionParameters": {
                "WFItems": {
                    "Value": {
                        "WFDictionaryFieldValueItems": [
                            {
                                "WFItemType": 0,
                                "WFKey": {
                                    "Value": {
                                        "string": "filepath"
                                    },
                                    "WFSerializationType": "WFTextTokenString"
                                },
                                "WFValue": {
                                    "Value": {
                                        "string": "￼",
                                        "attachmentsByRange": {
                                            "{0, 1}": {
                                                "OutputUUID": "8072BE04-FF3C-4C42-B193-630B85655D7E",
                                                "Type": "ActionOutput",
                                                "OutputName": "filepath"
                                            }
                                        }
                                    },
                                    "WFSerializationType": "WFTextTokenString"
                                }
                            },
                            {
                                "WFItemType": 0,
                                "WFKey": {
                                    "Value": {
                                        "string": "viewmode"
                                    },
                                    "WFSerializationType": "WFTextTokenString"
                                },
                                "WFValue": {
                                    "Value": {
                                        "string": "live"
                                    },
                                    "WFSerializationType": "WFTextTokenString"
                                }
                            }
                        ]
                    },
                    "WFSerializationType": "WFDictionaryFieldValue"
                },
                "UUID": "C3704966-147F-4829-96A6-414334F3755D"
            }
        },
        {
            "WFWorkflowActionIdentifier": "is.workflow.actions.date",
            "WFWorkflowActionParameters": {
                "CustomOutputName": "12:34",
                "UUID": "4654469C-0213-400D-9999-EB0F9B5295AD",
                "WFDateActionMode": "Specified Date",
                "WFDateActionDate": "12:34"
            }
        },
        {
            "WFWorkflowActionIdentifier": "is.workflow.actions.conditional",
            "WFWorkflowActionParameters": {
                "WFDate": {
                    "Value": {
                        "OutputUUID": "4654469C-0213-400D-9999-EB0F9B5295AD",
                        "Type": "ActionOutput",
                        "OutputName": "12:34"
                    },
                    "WFSerializationType": "WFTextTokenAttachment"
                },
                "WFInput": {
                    "Type": "Variable",
                    "Variable": {
                        "Value": {
                            "Type": "CurrentDate"
                        },
                        "WFSerializationType": "WFTextTokenAttachment"
                    }
                },
                "WFControlFlowMode": 0,
                "GroupingIdentifier": "CC53D381-3E3E-45B7-804C-526A0D464701",
                "WFCondition": 0
            }
        },
        {
            "WFWorkflowActionIdentifier": "is.workflow.actions.documentpicker.open",
            "WFWorkflowActionParameters": {
                "WFGetFilePath": {
                    "Value": {
                        "string": "￼",
                        "attachmentsByRange": {
                            "{0, 1}": {
                                "OutputUUID": "8072BE04-FF3C-4C42-B193-630B85655D7E",
                                "Type": "ActionOutput",
                                "OutputName": "filepath"
                            }
                        }
                    },
                    "WFSerializationType": "WFTextTokenString"
                },
                "WFFile": {
                    "fileLocation": {
                        "WFFileLocationType": "iCloud",
                        "fileProviderDomainID": "com.apple.CloudDocs.iCloudDriveFileProvider/94C360DB-8C66-408D-8531-5552FAD57577",
                        "relativeSubpath": "iCloud~md~obsidian/Documents/Second-Brain",
                        "appContainerBundleIdentifier": "md.obsidian",
                        "crossDeviceItemID": "docs.icloud.com:com.apple.CloudDocs/605C0ACE-E417-46F1-92D6-DCE07191E691/cd3551b64a22879ecb35ed82e0b007ce35786f8e"
                    },
                    "filename": "Second-Brain",
                    "displayName": "Second-Brain"
                },
                "UUID": "3DE54326-4ED6-4664-9006-B84B08DD8326"
            }
        },
        {
            "WFWorkflowActionIdentifier": "is.workflow.actions.text.split",
            "WFWorkflowActionParameters": {
                "text": {
                    "Value": {
                        "OutputUUID": "3DE54326-4ED6-4664-9006-B84B08DD8326",
                        "Type": "ActionOutput",
                        "OutputName": "File"
                    },
                    "WFSerializationType": "WFTextTokenAttachment"
                },
                "UUID": "96D6FE8C-3B28-4EEC-AD25-13647AD61977"
            }
        },
        {
            "WFWorkflowActionIdentifier": "is.workflow.actions.filter.files",
            "WFWorkflowActionParameters": {
                "WFContentItemInputParameter": {
                    "Value": {
                        "OutputUUID": "96D6FE8C-3B28-4EEC-AD25-13647AD61977",
                        "Type": "ActionOutput",
                        "OutputName": "Split Text"
                    },
                    "WFSerializationType": "WFTextTokenAttachment"
                },
                "WFContentItemLimitEnabled": true,
                "UUID": "D8B53102-3559-4157-BB53-A10B66110A1D",
                "WFContentItemLimitNumber": 1,
                "WFContentItemFilter": {
                    "Value": {
                        "WFActionParameterFilterPrefix": 1,
                        "WFContentPredicateBoundedDate": false,
                        "WFActionParameterFilterTemplates": [
                            {
                                "Operator": 8,
                                "Values": {
                                    "Unit": 4,
                                    "String": ">"
                                },
                                "Removable": true,
                                "Property": "Name"
                            }
                        ]
                    },
                    "WFSerializationType": "WFContentPredicateTableTemplate"
                }
            }
        },
        {
            "WFWorkflowActionIdentifier": "is.workflow.actions.dictionary",
            "WFWorkflowActionParameters": {
                "WFItems": {
                    "Value": {
                        "WFDictionaryFieldValueItems": [
                            {
                                "WFItemType": 0,
                                "WFKey": {
                                    "Value": {
                                        "string": "item"
                                    },
                                    "WFSerializationType": "WFTextTokenString"
                                },
                                "WFValue": {
                                    "Value": {
                                        "string": "￼",
                                        "attachmentsByRange": {
                                            "{0, 1}": {
                                                "OutputUUID": "D8B53102-3559-4157-BB53-A10B66110A1D",
                                                "Type": "ActionOutput",
                                                "OutputName": "Files"
                                            }
                                        }
                                    },
                                    "WFSerializationType": "WFTextTokenString"
                                }
                            },
                            {
                                "WFItemType": 0,
                                "WFKey": {
                                    "Value": {
                                        "string": "list"
                                    },
                                    "WFSerializationType": "WFTextTokenString"
                                },
                                "WFValue": {
                                    "Value": {
                                        "string": "￼",
                                        "attachmentsByRange": {
                                            "{0, 1}": {
                                                "OutputUUID": "96D6FE8C-3B28-4EEC-AD25-13647AD61977",
                                                "Type": "ActionOutput",
                                                "OutputName": "Split Text"
                                            }
                                        }
                                    },
                                    "WFSerializationType": "WFTextTokenString"
                                }
                            }
                        ]
                    },
                    "WFSerializationType": "WFDictionaryFieldValue"
                },
                "UUID": "BED1249D-905F-45C4-8B27-9B4A3F4C3B38"
            }
        },
        {
            "WFWorkflowActionIdentifier": "is.workflow.actions.runworkflow",
            "WFWorkflowActionParameters": {
                "WFInput": {
                    "Value": {
                        "OutputUUID": "BED1249D-905F-45C4-8B27-9B4A3F4C3B38",
                        "Type": "ActionOutput",
                        "OutputName": "Dictionary"
                    },
                    "WFSerializationType": "WFTextTokenAttachment"
                },
                "WFWorkflow": {
                    "workflowIdentifier": "0E5FA7A2-FBEE-4233-8B9E-F9959F316120",
                    "workflowName": "Get Index of List Item (First Occurrence)",
                    "isSelf": false
                },
                "UUID": "47534227-4EBD-481C-B0F9-DE285B29457B",
                "WFWorkflowName": "Get Index of List Item (First Occurrence)"
            }
        },
        {
            "WFWorkflowActionIdentifier": "is.workflow.actions.setvalueforkey",
            "WFWorkflowActionParameters": {
                "WFDictionaryValue": {
                    "Value": {
                        "string": "￼",
                        "attachmentsByRange": {
                            "{0, 1}": {
                                "OutputUUID": "47534227-4EBD-481C-B0F9-DE285B29457B",
                                "Type": "ActionOutput",
                                "OutputName": "Shortcut Result"
                            }
                        }
                    },
                    "WFSerializationType": "WFTextTokenString"
                },
                "UUID": "0EBB6684-D9B4-446A-A580-80D94EC41FE9",
                "WFDictionary": {
                    "Value": {
                        "OutputUUID": "C3704966-147F-4829-96A6-414334F3755D",
                        "Type": "ActionOutput",
                        "OutputName": "Dictionary"
                    },
                    "WFSerializationType": "WFTextTokenAttachment"
                },
                "WFDictionaryKey": "line"
            }
        },
        {
            "WFWorkflowActionIdentifier": "is.workflow.actions.conditional",
            "WFWorkflowActionParameters": {
                "GroupingIdentifier": "CC53D381-3E3E-45B7-804C-526A0D464701",
                "WFControlFlowMode": 1
            }
        },
        {
            "WFWorkflowActionIdentifier": "is.workflow.actions.setvalueforkey",
            "WFWorkflowActionParameters": {
                "WFDictionaryValue": "last",
                "UUID": "8F5EBC5C-CDDE-4A32-9DD9-BAC4FC84300E",
                "WFDictionary": {
                    "Value": {
                        "OutputUUID": "C3704966-147F-4829-96A6-414334F3755D",
                        "Type": "ActionOutput",
                        "OutputName": "Dictionary"
                    },
                    "WFSerializationType": "WFTextTokenAttachment"
                },
                "WFDictionaryKey": "line"
            }
        },
        {
            "WFWorkflowActionIdentifier": "is.workflow.actions.conditional",
            "WFWorkflowActionParameters": {
                "WFControlFlowMode": 2,
                "GroupingIdentifier": "CC53D381-3E3E-45B7-804C-526A0D464701",
                "UUID": "6EBC9E9D-F550-4108-8569-A2B0CA3F761D"
            }
        },
        {
            "WFWorkflowActionIdentifier": "is.workflow.actions.repeat.each",
            "WFWorkflowActionParameters": {
                "WFControlFlowMode": 2,
                "GroupingIdentifier": "B7D2A558-BE69-4152-A300-AC763CF37D31",
                "UUID": "4E21E383-35AC-4205-93F5-06C20E57EF50"
            }
        },
        {
            "WFWorkflowActionIdentifier": "is.workflow.actions.runworkflow",
            "WFWorkflowActionParameters": {
                "WFInput": {
                    "Value": {
                        "OutputUUID": "4E21E383-35AC-4205-93F5-06C20E57EF50",
                        "Type": "ActionOutput",
                        "OutputName": "Repeat Results"
                    },
                    "WFSerializationType": "WFTextTokenAttachment"
                },
                "WFWorkflow": {
                    "workflowIdentifier": "2EFCE47D-B1E1-4C88-AA1C-C455C2C13913",
                    "workflowName": "Obsidian - Open Note",
                    "isSelf": false
                },
                "UUID": "DC9699DF-BC81-4AE4-8393-EB42A4D5CB36",
                "WFWorkflowName": "Obsidian - Open Note"
            }
        },
        {
            "WFWorkflowActionIdentifier": "is.workflow.actions.exit",
            "WFWorkflowActionParameters": {}
        }
    ],
    "WFWorkflowInputContentItemClasses": [
        "WFDateContentItem"
    ],
    "WFWorkflowImportQuestions": [],
    "WFWorkflowTypes": [
        "WFWorkflowTypeShowInSearch"
    ],
    "WFQuickActionSurfaces": [],
    "WFWorkflowHasShortcutInputVariables": true
}